_fastdi_core.pyi
_fastdi_core/_fastdi_core.abi3.so
_fastdi_core/__init__.py
_fastdi_core/__init__.pyi
_fastdi_core/py.typed
fastdi/types.py
fastdi/__init__.py
fastdi/container.py
fastdi/py.typed
fastdi/decorators.py
fastdi_core-0.1.4.dist-info/METADATA
fastdi_core-0.1.4.dist-info/WHEEL
fastdi_core-0.1.4.dist-info/RECORD
