Metadata-Version: 2.4
Name: fastdi-core
Version: 0.1.4
Classifier: Programming Language :: Python
Classifier: Programming Language :: Python :: 3
Classifier: Programming Language :: Rust
Classifier: Programming Language :: Python :: Implementation :: CPython
Classifier: License :: OSI Approved :: MIT License
Classifier: Operating System :: OS Independent
Summary: FastDI — Rust-powered Dependency Injection for Python
Author-email: Ali Aliyev <ali@aliev.me>
License: MIT
Requires-Python: >=3.9
Project-URL: homepage, https://github.com/aliev/fastdi
